roombapy/__init__.py
roombapy/assets/FreeMono.ttf
roombapy/assets/home.png
roombapy/assets/j7_icon.png
roombapy/assets/m6_icon.png
roombapy/assets/monaco.ttf
roombapy/assets/overlay-battery-low.png
roombapy/assets/overlay-bin-full.png
roombapy/assets/overlay-cancelled.png
roombapy/assets/overlay-charging.png
roombapy/assets/overlay-error.png
roombapy/assets/overlay-tank-low.png
roombapy/assets/r865_icon.png
roombapy/assets/s9_icon.png
roombapy/const.py
roombapy/discovery.py
roombapy/entry_points.py
roombapy/getpassword.py
roombapy/mapping/__init__.py
roombapy/mapping/const.py
roombapy/mapping/image_helpers.py
roombapy/mapping/math_helpers.py
roombapy/mapping/misc_helpers.py
roombapy/mapping/roomba_icon_set.py
roombapy/mapping/roomba_map.py
roombapy/mapping/roomba_map_device.py
roombapy/mapping/roomba_mapper.py
roombapy/remote_client.py
roombapy/roomba.py
roombapy/roomba_factory.py
roombapy/roomba_info.py
roombasdk-1.7.10.dist-info/entry_points.txt
roombasdk-1.7.10.dist-info/LICENSE
roombasdk-1.7.10.dist-info/WHEEL
roombasdk-1.7.10.dist-info/METADATA
roombasdk-1.7.10.dist-info/RECORD
